pimpmyform/__init__.py
pimpmyform-0.0.1.dev1.dist-info/LICENSE
pimpmyform-0.0.1.dev1.dist-info/METADATA
pimpmyform-0.0.1.dev1.dist-info/WHEEL
pimpmyform-0.0.1.dev1.dist-info/top_level.txt
pimpmyform-0.0.1.dev1.dist-info/zip-safe
pimpmyform-0.0.1.dev1.dist-info/RECORD
