Metadata-Version: 2.1
Name: pimpmyform
Version: 0.0.1.dev1
Summary: "Data/request (Flask) processing."
Home-page: https://github.com/gurgy11/pimpmydb
Author: Gregory Bockus
Author-email: "gregory.bockus@gmail.com"
License: UNKNOWN
Project-URL: Bug Tracker, https://github.com/gurgy11/pimpmydb/issues
Platform: UNKNOWN
Classifier: Programming Language :: Python :: 3
Classifier: License :: OSI Approved :: MIT License
Classifier: Operating System :: OS Independent
Requires-Python: >=3.6
Requires-Dist: python-dotenv
